borsh_construct_tmp/__init__.py
borsh_construct_tmp/core.py
borsh_construct_tmp/enum.py
borsh_construct_tmp/py.typed
borsh_construct_tmp-0.1.0.dist-info/LICENSE
borsh_construct_tmp-0.1.0.dist-info/WHEEL
borsh_construct_tmp-0.1.0.dist-info/METADATA
borsh_construct_tmp-0.1.0.dist-info/RECORD
