Metadata-Version: 2.1
Name: borsh-construct-tmp
Version: 0.1.0
Summary: TEMPORARY LOCATION: DO NOT USE.
Home-page: https://github.com/near/borsh-construct-py
License: MIT
Author: kevinheavey
Author-email: kevinheavey123@gmail.com
Requires-Python: >=3.8.3,<4.0.0
Classifier: License :: OSI Approved :: MIT License
Classifier: Programming Language :: Python :: 3
Classifier: Programming Language :: Python :: 3.9
Requires-Dist: construct-typing (>=0.5.1,<0.6.0)
Requires-Dist: sumtypes (>=0.1a5,<0.2)
Project-URL: Repository, https://github.com/near/borsh-construct-py
